collective.transmogrifier-3.0.0-py3.8-nspkg.pth
collective/transmogrifier/__init__.py
collective/transmogrifier/configure.zcml
collective/transmogrifier/genericsetup.py
collective/transmogrifier/interfaces.py
collective/transmogrifier/meta.py
collective/transmogrifier/meta.zcml
collective/transmogrifier/transmogrifier.py
collective/transmogrifier/utils.py
collective/transmogrifier/sections/__init__.py
collective/transmogrifier/sections/breakpoint.py
collective/transmogrifier/sections/codec.py
collective/transmogrifier/sections/condition.py
collective/transmogrifier/sections/configure.zcml
collective/transmogrifier/sections/constructor.py
collective/transmogrifier/sections/csvsource.py
collective/transmogrifier/sections/dirwalker.py
collective/transmogrifier/sections/folders.py
collective/transmogrifier/sections/inserter.py
collective/transmogrifier/sections/listsource.py
collective/transmogrifier/sections/logger.py
collective/transmogrifier/sections/manipulator.py
collective/transmogrifier/sections/pathresolver.py
collective/transmogrifier/sections/savepoint.py
collective/transmogrifier/sections/splitter.py
collective/transmogrifier/sections/testing.zcml
collective/transmogrifier/sections/tests.py
collective/transmogrifier/sections/urlopener.py
collective/transmogrifier/sections/xmlwalker.py
collective/transmogrifier/tests/__init__.py
collective/transmogrifier/tests/csvsource.csv
collective/transmogrifier/tests/keysource.csv
collective/transmogrifier/tests/sample.csv
collective/transmogrifier/tests/test_transmogrifier.py
collective/transmogrifier/tests/urlopener.csv
collective.transmogrifier-3.0.0.dist-info/LICENSE.GPL
collective.transmogrifier-3.0.0.dist-info/LICENSE.txt
collective.transmogrifier-3.0.0.dist-info/METADATA
collective.transmogrifier-3.0.0.dist-info/WHEEL
collective.transmogrifier-3.0.0.dist-info/entry_points.txt
collective.transmogrifier-3.0.0.dist-info/namespace_packages.txt
collective.transmogrifier-3.0.0.dist-info/top_level.txt
collective.transmogrifier-3.0.0.dist-info/RECORD
