Metadata-Version: 2.1
Name: collective.transmogrifier
Version: 3.0.0
Summary: A configurable pipeline, aimed at transforming content for import and export
Home-page: https://github.com/collective/collective.transmogrifier
Author: Jarn
Author-email: info@jarn.com
License: GPL version 2
Project-URL: PyPI, https://pypi.python.org/pypi/collective.transmogrifier
Project-URL: Source, https://github.com/collective/collective.transmogrifier
Project-URL: Tracker, https://github.com/collective/collective.transmogrifier/issues
Keywords: content import filtering
Platform: UNKNOWN
Classifier: Development Status :: 6 - Mature
Classifier: Environment :: Web Environment
Classifier: Framework :: Plone :: 5.2
Classifier: Framework :: Plone :: 6.0
Classifier: Framework :: Plone :: Addon
Classifier: Framework :: Plone
Classifier: Framework :: Zope2
Classifier: Framework :: Zope3
Classifier: License :: OSI Approved :: GNU General Public License (GPL)
Classifier: License :: OSI Approved :: GNU General Public License v2 (GPLv2)
Classifier: Operating System :: OS Independent
Classifier: Programming Language :: Python :: 3.7
Classifier: Programming Language :: Python :: 3.8
Classifier: Programming Language :: Python :: 3.9
Classifier: Programming Language :: Python
Classifier: Topic :: Software Development :: Libraries :: Application Frameworks
Classifier: Topic :: Software Development :: Libraries :: Python Modules
Requires-Python: >=3.7
License-File: LICENSE.GPL
License-File: LICENSE.txt
Requires-Dist: Products.CMFCore
Requires-Dist: setuptools
Requires-Dist: zope.schema
Provides-Extra: test
Requires-Dist: zest.releaser[recommended] ; extra == 'test'
Requires-Dist: zope.testrunner ; extra == 'test'
